acorn/__init__.py
acorn/acrn.py
acorn/base.py
acorn/config.py
acorn/importer.py
acorn/ipython.py
acorn/msg.py
acorn/utility.py
acorn/analyze/__init__.py
acorn/analyze/sklearn.py
acorn/config/__builtin__.cfg
acorn/config/acorn.cfg
acorn/config/matplotlib.cfg
acorn/config/numpy.cfg
acorn/config/pandas.cfg
acorn/config/pandas.extras.json
acorn/config/pandas.json
acorn/config/pywt.cfg
acorn/config/scipy.cfg
acorn/config/sklearn.cfg
acorn/js/ipython.js
acorn/logging/__init__.py
acorn/logging/analysis.py
acorn/logging/database.py
acorn/logging/decoration.py
acorn/logging/descriptors.py
acorn/logging/diff.py
acorn/matplotlib/__init__.py
acorn/scipy/__init__.py
acorn/sklearn/__init__.py
acorn/subclass/__init__.py
acorn/subclass/_numpy.py
acorn-0.0.15.data/scripts/acrn.py
acorn-0.0.15.dist-info/DESCRIPTION.rst
acorn-0.0.15.dist-info/METADATA
acorn-0.0.15.dist-info/RECORD
acorn-0.0.15.dist-info/WHEEL
acorn-0.0.15.dist-info/metadata.json
acorn-0.0.15.dist-info/top_level.txt
