Metadata-Version: 2.0
Name: acorn
Version: 0.0.15
Summary: Automated computational research notebook.
Home-page: https://github.com/rosenbrockc/acorn
Author: Conrad W Rosenbrock
Author-email: rosenbrockc@gmail.com
License: MIT
Platform: UNKNOWN
Classifier: Development Status :: 4 - Beta
Classifier: Intended Audience :: Science/Research
Classifier: Intended Audience :: Developers
Classifier: Natural Language :: English
Classifier: Operating System :: MacOS
Classifier: Operating System :: Microsoft :: Windows
Classifier: Programming Language :: Python
Classifier: Programming Language :: Python :: 2
Classifier: Programming Language :: Python :: 2.7
Classifier: Programming Language :: Python :: 3
Classifier: Programming Language :: Python :: 3.4
Classifier: Topic :: Scientific/Engineering
Requires-Dist: argparse
Requires-Dist: pyparsing
Requires-Dist: six
Requires-Dist: termcolor
